nsnet2_denoiser/__init__.py
nsnet2_denoiser/denoise.py
nsnet2_denoiser/enhance_onnx.py
nsnet2_denoiser/featurelib.py
nsnet2_denoiser/nsnet2-20ms-48k-baseline.onnx
nsnet2_denoiser/nsnet2-20ms-baseline.onnx
nsnet2_denoiser-0.2.3.dist-info/LICENSE
nsnet2_denoiser-0.2.3.dist-info/LICENSE-CODE
nsnet2_denoiser-0.2.3.dist-info/METADATA
nsnet2_denoiser-0.2.3.dist-info/WHEEL
nsnet2_denoiser-0.2.3.dist-info/top_level.txt
nsnet2_denoiser-0.2.3.dist-info/zip-safe
nsnet2_denoiser-0.2.3.dist-info/RECORD
