Metadata-Version: 2.1
Name: nsnet2-denoiser
Version: 0.2.3
Summary: NSNet2 Deep Noise Suppression (DNS) package
Home-page: https://github.com/NeonGeckoCom/nsnet2-denoiser
Author: Neongecko
Author-email: developers@neon.ai
License: CC-BY-4.0, MIT
Platform: UNKNOWN
Classifier: Intended Audience :: Developers
Classifier: Topic :: Multimedia :: Sound/Audio :: Speech
Classifier: Programming Language :: Python :: 3.6
Requires-Python: >3.6.0
Requires-Dist: onnxruntime
Requires-Dist: torch
Requires-Dist: numpy
Requires-Dist: soundfile
Requires-Dist: scipy
